looming_authz_rule_engine/__init__.py
looming_authz_rule_engine/authz_rule_engine.py
looming_authz_rule_engine/module_code.py
looming_authz_rule_engine-0.4.0.dist-info/METADATA
looming_authz_rule_engine-0.4.0.dist-info/WHEEL
looming_authz_rule_engine-0.4.0.dist-info/licenses/LICENSE.MD
looming_authz_rule_engine-0.4.0.dist-info/RECORD
