Metadata-Version: 2.4
Name: looming-authz-rule-engine
Version: 0.4.0
Summary: Looming Authz Rule Engine
Project-URL: Homepage, https://github.com/LoomingPlatform/looming-galaxy
Project-URL: Issues, https://github.com/LoomingPlatform/looming-galaxy/issues
Author-email: Looming <devteam@looming.zone>
License-Expression: EUPL-1.2
License-File: LICENSE.MD
Classifier: Operating System :: OS Independent
Classifier: Programming Language :: Python :: 3
Requires-Python: >=3.12
